paramunittest.py
setup.py
ParamUnittest.egg-info/PKG-INFO
ParamUnittest.egg-info/SOURCES.txt
ParamUnittest.egg-info/dependency_links.txt
ParamUnittest.egg-info/top_level.txt