Metadata-Version: 1.0
Name: ParamUnittest
Version: 0.2
Summary: Simple extension to have parametrized unit tests.
Home-page: https://github.com/rik0/ParamUnittest
Author: Enrico Franchi
Author-email: enrico.franchi@gmail.com
License: BSD
Keywords: unittest
Platform: UNKNOWN
Classifier: Topic :: Software Development :: Testing
Classifier: Development Status :: 4 - Beta
Classifier: Intended Audience :: Developers
Classifier: License :: OSI Approved :: BSD License
Classifier: Operating System :: OS Independent
Classifier: Programming Language :: Python :: 2.7
